pixiv_pixie/__init__.py
pixiv_pixie/core/__init__.py
pixiv_pixie/core/exceptions.py
pixiv_pixie/core/types.py
pixiv_pixie/utils/__init__.py
pixiv_pixie/utils/fp.py
pixiv_pixie/utils/singleton.py
tests/__init__.py
tests/test_core_types.py
tests/test_utils_fp.py
tests/test_utils_singleton.py
PixivPixie-0.1.1.dist-info/LICENSE.txt
PixivPixie-0.1.1.dist-info/METADATA
PixivPixie-0.1.1.dist-info/WHEEL
PixivPixie-0.1.1.dist-info/top_level.txt
PixivPixie-0.1.1.dist-info/RECORD
