Metadata-Version: 2.1
Name: PixivPixie
Version: 0.1.1
Summary: User-friendly Pixiv API based on PixivPy
Home-page: https://github.com/Xdynix/PixivPixie
Author: Xdynix
Author-email: Lizard.rar@gmail.com
License: Apache 2.0
Keywords: pixiv,api,pixivpy,pixiv_pixie
Platform: any
Classifier: Development Status :: 3 - Alpha
Classifier: License :: OSI Approved :: Apache Software License
Classifier: Operating System :: OS Independent
Classifier: Programming Language :: Python :: 3
Requires-Python: >=3.4
Requires-Dist: attrs (>=19.0.0)
Requires-Dist: pixivpy (>=3.3.0)
Requires-Dist: requests (>=2.0.0)
